<?xml version="1.0" encoding="UTF-8" standalone="yes"?>
<p:sld xmlns:a="http://schemas.openxmlformats.org/drawingml/2006/main" xmlns:r="http://schemas.openxmlformats.org/officeDocument/2006/relationships" xmlns:p="http://schemas.openxmlformats.org/presentationml/2006/main"><p:cSld><p:spTree><p:nvGrpSpPr><p:cNvPr id="1" name="Shape 229"/><p:cNvGrpSpPr/><p:nvPr/></p:nvGrpSpPr><p:grpSpPr><a:xfrm><a:off x="0" y="0"/><a:ext cx="0" cy="0"/><a:chOff x="0" y="0"/><a:chExt cx="0" cy="0"/></a:xfrm></p:grpSpPr><p:pic><p:nvPicPr><p:cNvPr id="230" name="Google Shape;230;p34" descr="Image for post"/><p:cNvPicPr preferRelativeResize="0"/><p:nvPr/></p:nvPicPr><p:blipFill><a:blip r:embed="rId3"><a:alphaModFix/></a:blip><a:stretch><a:fillRect/></a:stretch></p:blipFill><p:spPr><a:xfrm><a:off x="2205963" y="147075"/><a:ext cx="4732063" cy="2065650"/></a:xfrm><a:prstGeom prst="rect"><a:avLst/></a:prstGeom><a:noFill/><a:ln><a:noFill/></a:ln></p:spPr></p:pic><p:sp><p:nvSpPr><p:cNvPr id="231" name="Google Shape;231;p34"/><p:cNvSpPr txBox="1"><a:spLocks noGrp="1"/></p:cNvSpPr><p:nvPr><p:ph type="ctrTitle" idx="2"/></p:nvPr></p:nvSpPr><p:spPr><a:xfrm><a:off x="412885" y="361692"/><a:ext cx="1793100" cy="427500"/></a:xfrm><a:prstGeom prst="rect"><a:avLst/></a:prstGeom></p:spPr><p:txBody><a:bodyPr spcFirstLastPara="1" wrap="square" lIns="91425" tIns="91425" rIns="91425" bIns="91425" anchor="b" anchorCtr="0"><a:noAutofit/></a:bodyPr><a:lstStyle/><a:p><a:pPr marL="0" lvl="0" indent="0" algn="l" rtl="0"><a:spcBef><a:spcPts val="0"/></a:spcBef><a:spcAft><a:spcPts val="0"/></a:spcAft><a:buNone/></a:pPr><a:r><a:rPr lang="en"><a:latin typeface="Comic Sans MS"/><a:ea typeface="Comic Sans MS"/><a:cs typeface="Comic Sans MS"/><a:sym typeface="Comic Sans MS"/></a:rPr><a:t>“Two-branch multi-stage” CNN</a:t></a:r><a:endParaRPr><a:latin typeface="Comic Sans MS"/><a:ea typeface="Comic Sans MS"/><a:cs typeface="Comic Sans MS"/><a:sym typeface="Comic Sans MS"/></a:endParaRPr></a:p></p:txBody></p:sp><p:sp><p:nvSpPr><p:cNvPr id="232" name="Google Shape;232;p34"/><p:cNvSpPr txBox="1"><a:spLocks noGrp="1"/></p:cNvSpPr><p:nvPr><p:ph type="ctrTitle" idx="3"/></p:nvPr></p:nvSpPr><p:spPr><a:xfrm><a:off x="309810" y="2453561"/><a:ext cx="1793100" cy="427500"/></a:xfrm><a:prstGeom prst="rect"><a:avLst/></a:prstGeom></p:spPr><p:txBody><a:bodyPr spcFirstLastPara="1" wrap="square" lIns="91425" tIns="91425" rIns="91425" bIns="91425" anchor="b" anchorCtr="0"><a:noAutofit/></a:bodyPr><a:lstStyle/><a:p><a:pPr marL="0" lvl="0" indent="0" algn="l" rtl="0"><a:spcBef><a:spcPts val="0"/></a:spcBef><a:spcAft><a:spcPts val="0"/></a:spcAft><a:buNone/></a:pPr><a:r><a:rPr lang="en"><a:latin typeface="Comic Sans MS"/><a:ea typeface="Comic Sans MS"/><a:cs typeface="Comic Sans MS"/><a:sym typeface="Comic Sans MS"/></a:rPr><a:t>Confidence Maps</a:t></a:r><a:endParaRPr><a:latin typeface="Comic Sans MS"/><a:ea typeface="Comic Sans MS"/><a:cs typeface="Comic Sans MS"/><a:sym typeface="Comic Sans MS"/></a:endParaRPr></a:p></p:txBody></p:sp><p:sp><p:nvSpPr><p:cNvPr id="233" name="Google Shape;233;p34"/><p:cNvSpPr txBox="1"><a:spLocks noGrp="1"/></p:cNvSpPr><p:nvPr><p:ph type="ctrTitle" idx="7"/></p:nvPr></p:nvSpPr><p:spPr><a:xfrm><a:off x="4095847" y="2453561"/><a:ext cx="1793100" cy="427500"/></a:xfrm><a:prstGeom prst="rect"><a:avLst/></a:prstGeom></p:spPr><p:txBody><a:bodyPr spcFirstLastPara="1" wrap="square" lIns="91425" tIns="91425" rIns="91425" bIns="91425" anchor="b" anchorCtr="0"><a:noAutofit/></a:bodyPr><a:lstStyle/><a:p><a:pPr marL="0" lvl="0" indent="0" algn="r" rtl="0"><a:spcBef><a:spcPts val="0"/></a:spcBef><a:spcAft><a:spcPts val="0"/></a:spcAft><a:buNone/></a:pPr><a:r><a:rPr lang="en"><a:latin typeface="Comic Sans MS"/><a:ea typeface="Comic Sans MS"/><a:cs typeface="Comic Sans MS"/><a:sym typeface="Comic Sans MS"/></a:rPr><a:t>Affinity Fields</a:t></a:r><a:endParaRPr><a:latin typeface="Comic Sans MS"/><a:ea typeface="Comic Sans MS"/><a:cs typeface="Comic Sans MS"/><a:sym typeface="Comic Sans MS"/></a:endParaRPr></a:p></p:txBody></p:sp><p:sp><p:nvSpPr><p:cNvPr id="234" name="Google Shape;234;p34"/><p:cNvSpPr txBox="1"><a:spLocks noGrp="1"/></p:cNvSpPr><p:nvPr><p:ph type="subTitle" idx="8"/></p:nvPr></p:nvSpPr><p:spPr><a:xfrm><a:off x="5047299" y="3864823"/><a:ext cx="1793100" cy="1003200"/></a:xfrm><a:prstGeom prst="rect"><a:avLst/></a:prstGeom></p:spPr><p:txBody><a:bodyPr spcFirstLastPara="1" wrap="square" lIns="91425" tIns="91425" rIns="91425" bIns="91425" anchor="t" anchorCtr="0"><a:noAutofit/></a:bodyPr><a:lstStyle/><a:p><a:pPr marL="0" lvl="0" indent="0" algn="r" rtl="0"><a:spcBef><a:spcPts val="0"/></a:spcBef><a:spcAft><a:spcPts val="0"/></a:spcAft><a:buNone/></a:pPr><a:endParaRPr/></a:p></p:txBody></p:sp><p:pic><p:nvPicPr><p:cNvPr id="235" name="Google Shape;235;p34" descr="Image for post"/><p:cNvPicPr preferRelativeResize="0"/><p:nvPr/></p:nvPicPr><p:blipFill><a:blip r:embed="rId4"><a:alphaModFix/></a:blip><a:stretch><a:fillRect/></a:stretch></p:blipFill><p:spPr><a:xfrm><a:off x="760375" y="3049750"/><a:ext cx="2054973" cy="1818275"/></a:xfrm><a:prstGeom prst="rect"><a:avLst/></a:prstGeom><a:noFill/><a:ln><a:noFill/></a:ln></p:spPr></p:pic><p:pic><p:nvPicPr><p:cNvPr id="236" name="Google Shape;236;p34" descr="16 Human Body Measurement System Using Open Cv - Body Measurement Info"/><p:cNvPicPr preferRelativeResize="0"/><p:nvPr/></p:nvPicPr><p:blipFill><a:blip r:embed="rId5"><a:alphaModFix/></a:blip><a:stretch><a:fillRect/></a:stretch></p:blipFill><p:spPr><a:xfrm><a:off x="4746525" y="3049750"/><a:ext cx="4286250" cy="1818275"/></a:xfrm><a:prstGeom prst="rect"><a:avLst/></a:prstGeom><a:noFill/><a:ln><a:noFill/></a:ln></p:spPr></p:pic></p:spTree></p:cSld><p:clrMapOvr><a:masterClrMapping/></p:clrMapOvr></p:sld>